{
  "id": "C6uHc0_ISvy",
  "title": "Video by flojt76",
  "description": "Hand-eye-coordination using a @hecostix 💫",
  "uploader": "Stefan Flöjt",
  "uploader_id": "229931467",
  "uploader_url": null,
  "channel": "flojt76",
  "upload_date": "20240508",
  "timestamp": 1715199496,
  "duration": 19.636,
  "view_count": null,
  "like_count": 134,
  "comment_count": 1,
  "thumbnail": "https://scontent-zrh1-1.cdninstagram.com/v/t51.71878-15/501517600_1394995628203858_298396988959631138_n.jpg?stp=dst-jpg_e35_s1080x1080_sh2.08_tt6&efg=eyJ2ZW5jb2RlX3RhZyI6ImltYWdlX3VybGdlbi4xOTE2LnNkci52aWRlb19kZWZhdWx0X2NvdmVyX2ZyYW1lLmMyIn0&_nc_ht=scontent-zrh1-1.cdninstagram.com&_nc_cat=110&_nc_oc=Q6cZ2gGvD3Xt9ejBwuKvBD39nRZQv89Z7rSu16U4CmkLYFgn0KrC9gNhpojP02Dm9oV297g&_nc_ohc=DH4M6k_iQN4Q7kNvwEsI8vU&_nc_gid=m6WvCnfsIsJuTa3wb4uQ_Q&edm=ANTKIIoBAAAA&ccb=7-5&oh=00_Af4TK-CCaSklT9jrVg5EGu7PE-pWXKOGIyYYfVdahvqR4w&oe=6A016333&_nc_sid=d885a2",
  "webpage_url": "https://www.instagram.com/p/C6uHc0_ISvy/",
  "extractor": "Instagram"
}