{
  "id": "DVCJkfqjCUS",
  "title": "Video by jamesbrennanofficial",
  "description": "Spider Partner Race! 🕷️😂\n\nPlayers pair up in a low “spider” position and race each other while staying linked and controlled it looks hilarious, but it’s a serious little mover of a game 💨\n\n📌 What it trains:\n✅ Core strength and full-body tension\n✅ Coordination and balance\n✅ Upper-body and shoulder strength\n✅ Teamwork and loads of laughter\n\nPerfect for warm-ups, kids’ sessions or just adding a bit of chaos and fun to training 👊\n\n#FunConditioning\n#KidsFitness\n#CoreTraining\n#MovementSkills\n#TrainThroughPlay",
  "uploader": "James Brennan | Performance Coach",
  "uploader_id": "2031288558",
  "uploader_url": null,
  "channel": "jamesbrennanofficial",
  "upload_date": "20260221",
  "timestamp": 1771706183,
  "duration": 8.08,
  "view_count": null,
  "like_count": 5596,
  "comment_count": 19,
  "thumbnail": "https://scontent-zrh1-1.cdninstagram.com/v/t51.71878-15/640095344_26172980725674985_3620085771138743450_n.jpg?stp=dst-jpg_e15_tt6&efg=eyJ2ZW5jb2RlX3RhZyI6ImltYWdlX3VybGdlbi42NDAuc2RyLnZpZGVvX2RlZmF1bHRfY292ZXJfZnJhbWUuYzIifQ&_nc_ht=scontent-zrh1-1.cdninstagram.com&_nc_cat=101&_nc_oc=Q6cZ2gG89ekHbG_h5sRQgtFURkqZWMIqjDX4q6JPkPgQpjvXv2lI0MtZNzK0s0JJZo6qc1k&_nc_ohc=lBQpZF0nsXAQ7kNvwFjAYDl&_nc_gid=swDGmtISp3nUKJuTL3yNtg&edm=ANTKIIoBAAAA&ccb=7-5&oh=00_Af4nd4ZBf_zqnx3X92erfOeEnS-fyJyzs8p2kB_sRlB7wA&oe=6A01408A&_nc_sid=d885a2",
  "webpage_url": "https://www.instagram.com/p/DVCJkfqjCUS/",
  "extractor": "Instagram"
}